{
	"comment" : "This list holds all catgirl images stored on https://nyan.injabie3.moe/p/",
    "catgirls" : [
        {
			"url" : "29380901.jpg",
			"character" : "Original Character",
			"id" : "29380901",
			"is_pixiv" : true
		},
        {
			"url" : "32130456_p0.jpg",
			"character" : "Original Character",
			"id" : "32130456",
			"is_pixiv" : true
		},
        {
			"url" : "35751417_p0.jpg",
			"character" : "天音ぽるん, Original Character",
			"id" : "35751417",
			"is_pixiv" : true
		},
        {
			"url" : "36919305_p0.jpg",
			"id" : "36919305",
			"is_pixiv" : true
		},
        {
			"url" : "40796315_p0.jpg",
			"character" : "Original Character",
			"id" : "40796315",
			"is_pixiv" : true
		},
        {
			"url" : "41988699_p0.jpg",
			"character" : "Original Character",
			"id" : "41988699",
			"is_pixiv" : true
		},
        {
			"url" : "42997147_p0.jpg",
			"character" : "Original Character",
			"id" : "42997147",
			"is_pixiv" : true
		},
        {
			"url" : "43460271_p0.jpg",
			"character" : "Original Character",
			"id" : "43460271",
			"is_pixiv" : true
		},
        {
			"url" : "43797580_p0.jpg",
			"character" : "Original Character",
			"id" : "43797580",
			"is_pixiv" : true
		},
        {
			"url" : "51384688_p0.jpg",
			"character" : "Original Character",
			"id" : "51384688",
			"is_pixiv" : true
		},
        {
			"url" : "55532559_p0.png",
			"character" : "Original Character",
			"id" : "55532559",
			"is_pixiv" : true
		},
		{
			"url" : "LYihdaY.jpg",
			"id" : null, 
			"is_pixiv" : false
		},
        {
			"url" : "60108325_p0.jpg",
			"character" : "Original Character",
			"id" : "60108325",
			"is_pixiv" : true
		},
        {
			"url" : "57916708_p0.png",
			"character" : "Rem, Re:zero",
			"id" : "57916708",
			"is_pixiv" : true
		},
        {
			"url" : "61355328_p0.jpg",
			"character" : "Rem, Re:zero",
			"id" : "61355328",
			"is_pixiv" : true
		},
        {
			"url" : "46603873_p0.jpg",
			"character" : "Hoshizora Rin, Love Live! school idol project",
			"id" : "46603873",
			"is_pixiv" : true
		},
        {
			"url" : "46865424_p0.jpg",
			"character" : "Hoshizora Rin, Love Live! school idol project",
			"id" : "46865424",
			"is_pixiv" : true
		},
        {
			"url" : "48031387_p0.jpg",
			"character" : "First years, Love Live! school idol project",
			"id" : "48031387",
			"is_pixiv" : true
		},
        {
			"url" : "46838370_p0.png",
			"character" : "Hoshizora Rin, Love Live! school idol project",
			"id" : "46838370",
			"is_pixiv" : true
		},
        {
			"url" : "48541062_p0.jpg",
			"character" : "Julie Sigtuna, Absolute Duo",
			"id" : "48541062",
			"is_pixiv" : true
		},
        {
			"url" : "50745813_p0.jpg",
			"character" : "Hoshimiya Ichigo, Aikatsu!",
			"id" : "50745813",
			"is_pixiv" : true
		},
        {
			"url" : "412623_366923176672178_198722176825613_1154353_504142030_o.jpg",
			"character" : "Kaname Madoka and Akemi Homura, Puella Magi Madoka Magica",
			"id" : null, 
			"is_pixiv" : false
		},
		{
			"url" : "6599f9e1341bc4c2beea0ea4c4ca1e79.jpg",
			"id" : null, 
			"is_pixiv" : false},
		
        {
			"url" : "37766477.jpg",
			"character" : "Original Character",
			"id" : "37766477",
			"is_pixiv" : true
		},
		{
			"url" : "40484869.jpg",
			"character" : "Hoshizora Rin, Love Live! school idol project",
			"id" : "40484869",
			"is_pixiv" : true
		},
        {
			"url" : "49281446_p0.png",
			"character" : "Maekawa Miku and Hoshizora Rin, iM@S CG and Love Live!",
			"id" : "49281446",
			"is_pixiv" : true
		},
        {
			"url" : "53457316_p0.jpg",
			"character" : "Hoshizora Rin, Love Live! school idol project",
			"id" : "53457316",
			"is_pixiv" : true
		},
		{
			"url" : "Asada.Shino.full.1434466.jpg",
			"character" :"Asada Shino, Sword Art Online",
			"id" : null,
			"is_pixiv" : false},
        {
			"url" : "45067913.jpg",
			"character" : "Ayano Keiko, Sword Art Online",
			"id" : "45067913",
			"is_pixiv" : true
		},
        {
			"url" : "5477855.png",
			"character" : "Maekawa Miku, iDOLM@STER Cinderella Girls",
			"id" : "5477855",
			"is_pixiv" : true
		},
		{
			"url" : "49971419_p2_master1200.jpg",
			"id" : "49971419",
			"is_pixiv" : true
		},
        {
			"url" : "51718727_p0.png",
			"character" : "Maekawa Miku, iDOLM@STER Cinderella Girls",
			"id" : "51718727",
			"is_pixiv" : true
		},
        {
			"url" : "52796537_p0.png",
			"character" : "Maekawa Miku, iDOLM@STER Cinderella Girls",
			"id" : "52796537",
			"is_pixiv" : true
		},
        {
			"url" : "50834482_p0.png",
			"character" : "Hoshizora Rin and Maekawa Miku, Love Live! and iM@S CG",
			"id" : "50834482",
			"is_pixiv" : true
		},
        {
			"url" : "48915221_p0.png",
			"character" : "Maekawa Miku, iDOLM@STER Cinderella Girls",
			"id" : "48915221",
			"is_pixiv" : true
		},
        {
			"url" : "49971419_p0_master1200.jpg",
			"character" : "Maekawa Miku, iDOLM@STER Cinderella Girls",
			"id" : "49971419",
			"is_pixiv" : true
		},
        {
			"url" : "55605900_p0.jpg",
			"character" : "Maekawa Miku, iDOLM@STER Cinderella Girls",
			"id" : "55605900",
			"is_pixiv" : true
		},
        {
			"url" : "60181824_p0.png",
			"character" : "Maekawa Miku, iDOLM@STER Cinderella Girls",
			"id" : "60181824",
			"is_pixiv" : true
		},
		{
			"url" : "61439246_p0.png",
			"character" : "Original Character",
			"id" : "61439246",
			"is_pixiv" : true
		},
		{
			"url" : "61400112_p0.png",
			"id" : "61400112",
			"is_pixiv" : true
		},
		{
			"url" : "61048318_p1_master1200.jpg",
			"id" : "61048318",
			"is_pixiv" : true
		},
		{
			"url" : "60631364_p0.png",
			"id" : "60631364",
			"is_pixiv" : true
		},
		{
			"url" : "60246153_p0.png",
			"character" : "Frandle Scarlet, Touhou",
			"id" : "60246153",
			"is_pixiv" : true
		},
		{
			"url" : "59819032_p0.jpg",
			"character" : "Nishikino Maki, Love Live! school idol project",
			"id" : "59819032",
			"is_pixiv" : true
		},
		{
			"url" : "59968947_p0.jpg",
			"id" : "59968947",
			"is_pixiv" : true
		},
		{
			"url" : "61466602_p0.jpg",
			"character" : "Original Character",
			"id" : "61466602",
			"is_pixiv" : true
		},
		{
			"url" : "61449293_p0.jpg",
			"character" : "Original Character",
			"id" : "61449293",
			"is_pixiv" : true
		},
		{
			"url" : "61450692_p0.jpg",
			"character" : "Kisaragi, Kantai Collection",
			"id" : "61450692",
			"is_pixiv" : true
		},
		{
			"url" : "61304332_p0.png",
			"character" : "Original Character",
			"id" : "61304332",
			"is_pixiv" : true
		},
		{
			"url" : "61455603_p0.png",
			"character" : "Original Character",
			"id" : "61455603",
			"is_pixiv" : true
		},
		{
			"url" : "60727765_p0.png",
			"character" : "Original Character",
			"id" : "60727765",
			"is_pixiv" : true
		},
		{
			"url" : "54207682_p0.png",
			"character" : "Original Character",
			"id" : "54207682",
			"is_pixiv" : true
		},
		{
			"url" : "33724932_p2.jpg",
			"id" : "33724932",
			"is_pixiv" : true
		},
		{
			"url" : "56940288_p0.png",
			"character" : "Nishikino Maki, Love Live! school idol project",
			"id" : "56940288",
			"is_pixiv" : true
		},
		{
			"url" : "59744468_p0.jpg",
			"character" : "ChiMaMe-tai, Gochuumon wa Usagi desu ka?",
			"id" : "59744468",
			"is_pixiv" : true
		},
		{
			"url" : "46917991_p0.png",
			"character" : "Original Character",
			"id" : "46917991",
			"is_pixiv" : true
		},
		{
			"url" : "57304078_p0.png",
			"character" : "Original Character",
			"id" : "57304078",
			"is_pixiv" : true
		},
		{
			"url" : "55621663_p0.jpg",
			"character" : "Chocola and Vanilla, NEKOPARA",
			"id" : "55621663",
			"is_pixiv" : true
		},
		{
			"url" : "55382552_p3.png",
			"character" : "Maekawa Miku, iDOLM@STER Cinderella Girls",
			"id" : "55382552",
			"is_pixiv" : true
		},
		{
			"url" : "53474504_p0.jpg",
			"character" : "Maekawa Miku, iDOLM@STER Cinderella Girls",
			"id" : "53474504",
			"is_pixiv" : true
		},
		{
			"url" : "54191467_p0.png",
			"character" : "Original Character",
			"id" : "54191467",
			"is_pixiv" : true
		},
		{
			"url" : "51662663_p0.jpg",
			"character" : "Original Character",
			"id" : "51662663",
			"is_pixiv" : true
		},
		{
			"url" : "42395901_p0.jpg",
			"character" : "リリー，コロネ，ソーニャ， Original Characters",
			"id" : "42395901",
			"is_pixiv" : true
		},
		{
			"url" : "61538563_p0.jpg",
			"id" : "61538563",
			"is_pixiv" : true
		},
		{
			"url" : "61575360_p0.jpg",
			"character" : "Yazawa Nico and Nishikino Maki, Love Live! school idol project",
			"id" : "61575360",
			"is_pixiv" : true
		},
		{
			"url" : "61586026_p0.png",
			"character" : "Yazawa Nico and Nishikino Maki, Love Live! school idol project",
			"id" : "61586026",
			"is_pixiv" : true
		},
		{
			"url" : "61589608_p0.jpg",
			"character" : "Kamui Kanna, Kobayashi-san Chi no Maid Dragon",
			"id" : "61589608",
			"is_pixiv" : true
		},
		{
			"url" : "61671718_p0.png",
			"character" : "Original Character",
			"id" : "61671718",
			"is_pixiv" : true
		},
		{
			"url" : "61627632_p0.png",
			"character" : "Cyan, SHOW BY ROCK",
			"id" : "61627632",
			"is_pixiv" : true
		},
		{
			"url" : "61606829_p0.jpg",
			"character" : "IA, Vocaloid",
			"id" : "61606829",
			"is_pixiv" : true
		},
		{
			"url" : "61591523_p0.png",
			"character" : "Tojo Karen, Kiniro Mosaic",
			"id" : "61591523",
			"is_pixiv" : true
		},
		{
			"url" : "61591113_p0.png",
			"character" : "Original Character",
			"id" : "61591113",
			"is_pixiv" : true
		},
		{
			"url" : "61588275_p0.jpg",
			"character" : "Furutani Himawari and Omuro Sakurako, Yuru Yuri",
			"id" : "61588275",
			"is_pixiv" : true
		},
		{
			"url" : "61587038_p0.png",
			"character" : "Original Character",
			"id" : "61587038",
			"is_pixiv" : true
		},
		{
			"url" : "61582530_p0.jpg",
			"character" : "チョコミント， Original Character",
			"id" : "61582530",
			"is_pixiv" : true
		},
		{
			"url" : "61576250_p0.jpg",
			"character" : "Minami Kotori, Love Live! school idol project",
			"id" : "61576250",
			"is_pixiv" : true
		},
		{
			"url" : "61569203_p0.png",
			"id" : "61569203",
			"is_pixiv" : true
		},
		{
			"url" : "61499055_p0.jpg",
			"character" : "Haruna, Kantai Collection",
			"id" : "61499055",
			"is_pixiv" : true
		},
		{
			"url" : "61494168_p0.png",
			"character" : "Sakurauchi Riko, Love Live! Sunshine!!",
			"id" : "61494168",
			"is_pixiv" : true
		},
		{
			"url" : "56926503_p1.jpg",
			"character" : "Emilia, Re Zero",
			"id" : "56926503",
			"is_pixiv" : true
		},
		{
			"url" : "61738414_p0.jpg",
			"character" : "Misono Senri, Daitoshokan no Hitsujikai",
			"id" : "61738414",
			"is_pixiv" : true
		},
		{
			"url" : "61680548_p0.jpg",
			"character" : "Original Character",
			"id" : "61680548",
			"is_pixiv" : true
		},
		{
			"url" : "61436404_p0.png",
			"character" : "Original Character",
			"id" : "61436404",
			"is_pixiv" : true
		},
		{
			"url" : "61297270_p0.jpg",
			"character" : "Fubuki, Kantai Collection",
			"id" : "61297270",
			"is_pixiv" : true
		},
		{
			"url" : "61818399_p0.jpg",
			"character" : "Hatsune Miku, Vocaloid",
			"id" : "61818399",
			"is_pixiv" : true
		},
		{
			"url" : "61784409_p0.png",
			"character" : "Minami Kotori, Love Live! school idol project",
			"id" : "61784409",
			"is_pixiv" : true
		},
		{
			"url" : "61764381_p0.png",
			"id" : "61764381",
			"is_pixiv" : true
		},
		{
			"url" : "61749296_p0.png",
			"character" : "Original Character",
			"id" : "61749296",
			"is_pixiv" : true
		},
		{
			"url" : "61604344_p0.jpg",
			"character" : "Original Character",
			"id" : "61604344",
			"is_pixiv" : true
		},
		{
			"url" : "61170981_p0.png",
			"character" : "ショコラ, Original Character",
			"id" : "61170981",
			"is_pixiv" : true
		},
		{
			"url" : "61143623_p0.png",
			"character" : "Hibiki, Kantai Collection",
			"id" : "61143623",
			"is_pixiv" : true
		},
		{
			"url" : "60975519_p0.jpg",
			"character" : "Original Character",
			"id" : "60975519",
			"is_pixiv" : true
		},
		{
			"url" : "60966496_p0.jpg",
			"character" : "Original Character",
			"id" : "60966496",
			"is_pixiv" : true
		},
		{
			"url" : "60938931_p0.jpg",
			"character" : "Tedeza Rize, Gochuumon wa Usagi desu ka?",
			"id" : "60938931",
			"is_pixiv" : true
		},
		{
			"url" : "60922534_p0.jpg",
			"character" : "Ryuuhou, Kantai Collection",
			"id" : "60922534",
			"is_pixiv" : true
		},
		{
			"url" : "60920059_p0.png",
			"character" : "Original Character",
			"id" : "60920059",
			"is_pixiv" : true
		},
		{
			"url" : "60892037_p0.jpg",
			"character" : "Original Character",
			"id" : "60892037",
			"is_pixiv" : true
		},
		{
			"url" : "57305687_p0.jpg",
			"character" : "Original Character",
			"id" : "57305687",
			"is_pixiv" : true
		},
		{
			"url" : "61881723_p0.jpg",
			"character" : "Original Character",
			"id" : "61881723",
			"is_pixiv" : true
		},
		{
			"url" : "60808294_p0.jpg",
			"character" : "Original Character",
			"id" : "60808294",
			"is_pixiv" : true
		},
		{
			"url" : "61735071_p0.jpg",
			"character" : "Original Character",
			"id" : "61735071",
			"is_pixiv" : true
		},
		{
			"url" : "61862170_p0.png",
			"character" : "Original Character",
			"id" : "61862170",
			"is_pixiv" : true
		},
		{
			"url" : "60824245_p0.png",
			"character" : "Original Character",
			"id" : "60824245",
			"is_pixiv" : true
		},
		{
			"url" : "61890886_p0.jpg",
			"character" : "Original Character",
			"id" : "61890886",
			"is_pixiv" : true
		},
		{
			"url" : "61892046_p0.png",
			"character" : "Original Character",
			"id" : "61892046",
			"is_pixiv" : true
		},
		{
			"url" : "60723560_p0.jpg",
			"character" : "Original Character",
			"id" : "60723560",
			"is_pixiv" : true
		},
		{
			"url" : "60702703_p0.jpg",
			"character" : "Original Character",
			"id" : "60702703",
			"is_pixiv" : true
		},
		{
			"url" : "60659263_p0.jpg",
			"character" : "Rem, Re Zero",
			"id" : "60659263",
			"is_pixiv" : true
		},
		{
			"url" : "60612962_p0.png",
			"character" : "Maekawa Miku, The iDOLM@STER Cinderella Girls",
			"id" : "60612962",
			"is_pixiv" : true
		},
		{
			"url" : "60610435_p0.png",
			"character" : "Original Character",
			"id" : "60610435",
			"is_pixiv" : true
		},
		{
			"url" : "60562466_p0.jpg",
			"character" : "Original Character",
			"id" : "60562466",
			"is_pixiv" : true
		},
		{
			"url" : "60561920_p0.png",
			"character" : "Suzuya, Kantai Collection",
			"id" : "60561920",
			"is_pixiv" : true
		},
		{
			"url" : "60524708_p0.jpg",
			"character" : "Original Character",
			"id" : "60524708",
			"is_pixiv" : true
		},
		{
			"url" : "60513073_p0.jpg",
			"character" : "Original Character",
			"id" : "60513073",
			"is_pixiv" : true
		},
		{
			"url" : "60446625_p0.png",
			"id" : "60446625",
			"is_pixiv" : true
		},
		{
			"url" : "60442851_p0.jpg",
			"character" : "アメリ, Original Character",
			"id" : "60442851",
			"is_pixiv" : true
		},
		{
			"url" : "60416631_p0.jpg",
			"character" : "Original Character",
			"id" : "60416631",
			"is_pixiv" : true
		},
		{
			"url" : "60418891_p0.jpg",
			"character" : "Original Character",
			"id" : "60418891",
			"is_pixiv" : true
		},
		{
			"url" : "60401182_p0.jpg",
			"character" : "Original Character",
			"id" : "60401182",
			"is_pixiv" : true
		},
		{
			"url" : "60374747_p0.jpg",
			"character" : "Original Character",
			"id" : "60374747",
			"is_pixiv" : true
		},
		{
			"url" : "60299919_p0.png",
			"character" : "Original Characters",
			"id" : "60299919",
			"is_pixiv" : true
		},
		{
			"url" : "61925779_p0.png",
			"character" : "Sonoda Umi, Love Live! school idol project",
			"id" : "61925779",
			"is_pixiv" : true
		},
		{
			"url" : "61883735_p0.png",
			"character" : "Serval, Kemono Friends",
			"id" : "61883735",
			"is_pixiv" : true
		},
		{
			"url" : "59986465_p0.png",
			"character" : "Original Character",
			"id" : "59986465",
			"is_pixiv" : true
		},
		{
			"url" : "59968647_p0.png",
			"id" : "59968647",
			"is_pixiv" : true
		},
		{
			"url" : "59943924_p0.jpg",
			"character" : "Original Character",
			"id" : "59943924",
			"is_pixiv" : true
		},
		{
			"url" : "59927510_p0.jpg",
			"character" : "Watanabe You and Tsushima Yoshiko, Love Live! Sunshine!!",
			"id" : "59927510",
			"is_pixiv" : true
		},
		{
			"url" : "59912018_p0.png",
			"character" : "Original Character",
			"id" : "59912018",
			"is_pixiv" : true
		},
		{
			"url" : "59888327_p0.jpg",
			"character" : "Original Characters",
			"id" : "59888327",
			"is_pixiv" : true
		},
		{
			"url" : "59883090_p0.jpg",
			"character" : "Original Characters",
			"id" : "59883090",
			"is_pixiv" : true
		},
		{
			"url" : "59761845_p0.jpg",
			"character" : "Hoshizora Rin, Love Live! school idol project",
			"id" : "59761845",
			"is_pixiv" : true
		},
		{
			"url" : "60301280_p0.jpg",
			"character" : "Original Character",
			"id" : "60301280",
			"is_pixiv" : true
		},
		{
			"url" : "59144746_p0.jpg",
			"character" : "Kafuu Chino, Gochuumon wa Usagi desu ka?",
			"id" : "59144746",
			"is_pixiv" : true
		},
		{
			"url" : "58861743_p0.png",
			"character" : "Kafuu Chino, Gochuumon wa Usagi desu ka?",
			"id" : "58861743",
			"is_pixiv" : true
		},
		{
			"url" : "61492676_p0.png",
			"character" : "Original Character",
			"id" : "61492676",
			"is_pixiv" : true
		},
		{
			"url" : "61640017_p0.png",
			"character" : "Original Character",
			"id" : "61640017",
			"is_pixiv" : true
		},
		{
			"url" : "59351074_p0.png",
			"character" : "Original Character",
			"id" : "59351074",
			"is_pixiv" : true
		},
		{
			"url" : "55434269_p0.png",
			"character" : "Original Character",
			"id" : "55434269",
			"is_pixiv" : true
		},
		{
			"url" : "55517473_p0.jpg",
			"character" : "Original Character",
			"id" : "55517473",
			"is_pixiv" : true
		},
		{
			"url" : "61544409_p0.png",
			"character" : "Original Character",
			"id" : "61544409",
			"is_pixiv" : true
		},
		{
			"url" : "61509366_p0.jpg",
			"id" : "61509366",
			"is_pixiv" : true
		},
		{
			"url" : "61447060_p0.png",
			"character" : "Original Characters (beware the trap)",
			"id" : "61447060",
			"is_pixiv" : true
		},
		{
			"url" : "58835009_p0.jpg",
			"character" : "Hibiki, Kantai Collection",
			"id" : "58835009",
			"is_pixiv" : true
		},
		{
			"url" : "58779553_p0.png",
			"character" : "Rem, Re Zero",
			"id" : "58779553",
			"is_pixiv" : true
		},
		{
			"url" : "57278472_p0.jpg",
			"character" : "Freyja Wion, Macross Delta",
			"id" : "57278472",
			"is_pixiv" : true
		},
		{
			"url" : "56461718_p0.jpg",
			"character" : "Original Characters",
			"id" : "56461718",
			"is_pixiv" : true
		},
		{
			"url" : "56310621_p0.jpg",
			"character" : "Original Character",
			"id" : "56310621",
			"is_pixiv" : true
		},
		{
			"url" : "56034227_p0.jpg",
			"character" : "Original Character (beware the trap)",
			"id" : "56034227",
			"is_pixiv" : true
		},
		{
			"url" : "55798958_p0.jpg",
			"id" : "55798958",
			"is_pixiv" : true
		},
		{
			"url" : "55553879_p0.png",
			"character" : "Original Character",
			"id" : "55553879",
			"is_pixiv" : true
		},
		{
			"url" : "55232838_p0.jpg",
			"character" : "Original Characters",
			"id" : "55232838",
			"is_pixiv" : true
		},
		{
			"url" : "58816351_p0.png",
			"character" : "Original Character",
			"id" : "58816351",
			"is_pixiv" : true
		},
		{
			"url" : "60379919_p0.png",
			"character" : "Original Character",
			"kitsune" : true,
			"id" : "60379919",
			"is_pixiv" : true
		},
		{
			"url" : "59652188_p0.png",
			"character" : "Original Characters",
			"kitsune" : true,
			"id" : "59652188",
			"is_pixiv" : true
		},
		{
			"url" : "51816801_p0.jpg",
			"character" : "Original Character",
			"id" : "51816801",
			"is_pixiv" : true
		},
		{
			"url" : "50355629_p0.jpg",
			"character" : "Original Character",
			"id" : "50355629",
			"is_pixiv" : true
		},
		{
			"url" : "50302879_p0.jpg",
			"character" : "Cyan, SHOW BY ROCK!",
			"id" : "50302879",
			"is_pixiv" : true
		},
		{
			"url" : "50057588_p0.jpg",
			"character" : "Original Character",
			"id" : "50057588",
			"is_pixiv" : true
		},
		{
			"url" : "59730146_p0.jpg",
			"character" : "Hibiki, Kantai Collection",
			"id" : "59730146",
			"is_pixiv" : true
		},
		{
			"url" : "59223518_p0.png",
			"character" : "ショコラ, Original Character",
			"id" : "59223518",
			"is_pixiv" : true
		},
		{
			"url" : "59717756_p0.jpg",
			"character" : "Watanabe You, Love Live! Sunshine!!",
			"id" : "59717756",
			"is_pixiv" : true
		},
		{
			"url" : "59695608_p0.png",
			"character" : "Tama, Kantai Collection",
			"id" : "59695608",
			"is_pixiv" : true
		},
		{
			"url" : "58097381_p0.jpg",
			"character" : "Original Character",
			"kitsune" : true,
			"id" : "58097381",
			"is_pixiv" : true
		},
		{
			"url" : "26971098_p0.jpg",
			"character" : "Original Character",
			"id" : "26971098",
			"is_pixiv" : true
		},
		{
			"url" : "27041254_p0.jpg",
			"character" : "てぃん子, Original Character",
			"id" : "27041254",
			"is_pixiv" : true
		},
		{
			"url" : "52909357_p0.jpg",
			"character" : "Original Character",
			"id" : "52909357",
			"is_pixiv" : true
		},
		{
			"url" : "52534808_p0.jpg",
			"character" : "Original Character",
			"id" : "52534808",
			"is_pixiv" : true
		},
		{
			"url" : "61961955_p0.jpg",
			"character" : "Haruna, Kantai Collection",
			"id" : "61961955",
			"is_pixiv" : true
		},
		{
			"url" : "61958631_p0.png",
			"character" : "Original Character",
			"id" : "61958631",
			"is_pixiv" : true
		},
		{
			"url" : "61938169_p0.png",
			"character" : "Original Character",
			"id" : "61938169",
			"is_pixiv" : true
		},
		{
			"url" : "59537610_p0.jpg",
			"character" : "Original Character",
			"id" : "59537610",
			"is_pixiv" : true
		},
		{
			"url" : "59506515_p0.jpg",
			"character" : "Akebono, Kantai Collection",
			"id" : "59506515",
			"is_pixiv" : true
		},
		{
			"url" : "59471785_p0.jpg",
			"character" : "Maekawa Miku, iDOLM@STER Cinderella Girls",
			"id" : "59471785",
			"is_pixiv" : true
		},
		{
			"url" : "59467743_p0.png",
			"character" : "茶屋町・因六, Kerberos Blade",
			"id" : "59467743",
			"is_pixiv" : true
		},
		{
			"url" : "59431830_p0.jpg",
			"character" : "Hibiki, Kantai Collection",
			"id" : "59431830",
			"is_pixiv" : true
		},
		{
			"url" : "59374353_p0.png",
			"character" : "Rem, Re Zero",
			"id" : "59374353",
			"is_pixiv" : true
		},
		{
			"url" : "59340127_p0.png",
			"character" : "Original Character",
			"id" : "59340127",
			"is_pixiv" : true
		},
		{
			"url" : "59280510_p0.png",
			"character" : "Original Character",
			"id" : "59280510",
			"is_pixiv" : true
		},
		{
			"url" : "59272799_p0.jpg",
			"character" : "Kashima, Kantai Collection",
			"id" : "59272799",
			"is_pixiv" : true
		},
		{
			"url" : "59236968_p0.png",
			"character" : "Original Characters",
			"id" : "59236968",
			"is_pixiv" : true
		},
		{
			"url" : "59196059_p0.jpg",
			"character" : "Kaku Seiga, Touhou",
			"id" : "59196059",
			"is_pixiv" : true
		},
		{
			"url" : "59193496_p0.png",
			"character" : "ネージュ, Original Character",
			"id" : "59193496",
			"is_pixiv" : true
		},
		{
			"url" : "59092430_p0.jpg",
			"character" : "Akebono, Kantai Collection",
			"id" : "59092430",
			"is_pixiv" : true
		},
		{
			"url" : "59090050_p0.jpg",
			"character" : "Maekawa Miku, iDOLM@STER Cinderella Girls",
			"id" : "59090050",
			"is_pixiv" : true
		},
		{
			"url" : "62037490_p0.jpg",
			"character" : "アメリ, Original Character",
			"id" : "62037490",
			"is_pixiv" : true
		},
		{
			"url" : "62033891_p0.png",
			"character" : "Original Character",
			"id" : "62033891",
			"is_pixiv" : true
		},
		{
			"url" : "59030717_p0.png",
			"character" : "Original Character",
			"id" : "59030717",
			"is_pixiv" : true
		},
		{
			"url" : "59011521_p0.png",
			"character" : "Original Character",
			"id" : "59011521",
			"is_pixiv" : true
		},
		{
			"url" : "58957320_p0.jpg",
			"character" : "Rem, Re Zero",
			"id" : "58957320",
			"is_pixiv" : true
		},
		{
			"url" : "58962471_p0.png",
			"character" : "Hamakaze, Kantai Collection",
			"id" : "58962471",
			"is_pixiv" : true
		},
		{
			"url" : "58943725_p0.png",
			"character" : "Mimi, Re Zero",
			"id" : "58943725",
			"is_pixiv" : true
		},
		{
			"url" : "58930689_p0.png",
			"character" : "Asashio, Kantai Collection",
			"id" : "58930689",
			"is_pixiv" : true
		},
		{
			"url" : "58917798_p0.png",
			"character" : "Original Characters",
			"id" : "58917798",
			"is_pixiv" : true
		},
		{
			"url" : "58902607_p0.jpg",
			"character" : "Takimoto Hifumi and Suzukaze Aoba, NEW GAME!",
			"id" : "58902607",
			"is_pixiv" : true
		},
		{
			"url" : "58873424_p0.jpg",
			"character" : "Original Character",
			"id" : "58873424",
			"is_pixiv" : true
		},
		{
			"url" : "58870033_p0.png",
			"character" : "Felix, Re Zero (huehuehue)",
			"id" : "58870033",
			"is_pixiv" : true
		},
		{
			"url" : "58770133_p0.png",
			"character" : "Teruzuki, Kantai Collection",
			"id" : "58770133",
			"is_pixiv" : true
		},
		{
			"url" : "58767707_p0.jpg",
			"character" : "Suzukaze Aoba, NEW GAME!",
			"id" : "58767707",
			"is_pixiv" : true
		},
		{
			"url" : "58730601_p0.jpg",
			"character" : "Felix, Re Zero (kek)",
			"id" : "58730601",
			"is_pixiv" : true
		},
		{
			"url" : "58677398_p0.png",
			"character" : "Original Characters",
			"id" : "58677398",
			"is_pixiv" : true
		},
		{
			"url" : "58670817_p0.png",
			"character" : "Original Character",
			"id" : "58670817",
			"is_pixiv" : true
		},
		{
			"url" : "58644732_p0.png",
			"id" : "58644732",
			"is_pixiv" : true
		},
		{
			"url" : "58611020_p0.png",
			"character" : "Hamakaze, Kantai Collection",
			"id" : "58611020",
			"is_pixiv" : true
		},
		{
			"url" : "58581945_p0.png",
			"character" : "Rem, Re Zero",
			"id" : "58581945",
			"is_pixiv" : true
		},
		{
			"url" : "58582416_p0.png",
			"character" : "Felix, Re Zero (This one's cute, though)",
			"id" : "58582416",
			"is_pixiv" : true
		},
		{
			"url" : "58598978_p0.png",
			"character" : "Minazuki, Kantai Collection",
			"id" : "58598978",
			"is_pixiv" : true
		},
		{
			"url" : "58394029_p0.png",
			"character" : "Original Character",
			"id" : "58394029",
			"is_pixiv" : true
		},
		{
			"url" : "58367505_p0.png",
			"character" : "Rem, Re Zero",
			"id" : "58367505",
			"is_pixiv" : true
		},
		{
			"url" : "62084173_p0.jpg",
			"character" : "Original Character",
			"id" : "62084173",
			"is_pixiv" : true
		},
		{
			"url" : "58271049_p0.jpg",
			"id" : "58271049",
			"is_pixiv" : true
		},
		{
			"url" : "58154038_p0.jpg",
			"character" : "Original Character",
			"id" : "58154038",
			"is_pixiv" : true
		},
		{
			"url" : "58151284_p0.jpg",
			"character" : "Rem, Re Zero",
			"id" : "58151284",
			"is_pixiv" : true
		},
		{
			"url" : "58117996_p0.jpg",
			"character" : "Original Character",
			"id" : "58117996",
			"is_pixiv" : true
		},
		{
			"url" : "57963150_p0.png",
			"character" : "Yayoi, Kantai Collection",
			"id" : "57963150",
			"is_pixiv" : true
		},
		{
			"url" : "57944060_p0.png",
			"id" : "57944060",
			"is_pixiv" : true
		},
		{
			"url" : "57949099_p0.png",
			"character" : "Kashima, Kantai Collection",
			"id" : "57949099",
			"is_pixiv" : true
		},
		{
			"url" : "54921187_p0.png",
			"character" : "Kashima, Kantai Collection",
			"id" : "54921187",
			"is_pixiv" : true
		},
		{
			"url" : "57799325_p0.jpg",
			"character" : "Rem, Re Zero",
			"id" : "57799325",
			"is_pixiv" : true
		},
		{
			"url" : "57741459_p0.png",
			"id" : "57741459",
			"is_pixiv" : true
		},
		{
			"url" : "57707495_p0.jpg",
			"character" : "Original Character",
			"id" : "57707495",
			"is_pixiv" : true
		},
		{
			"url" : "57663652_p0.png",
			"character" : "Original Character",
			"id" : "57663652",
			"is_pixiv" : true
		},
		{
			"url" : "57502956_p0.jpg",
			"character" : "Original Character",
			"id" : "57502956",
			"is_pixiv" : true
		},
		{
			"url" : "58067635_p0.png",
			"id" : "58067635",
			"is_pixiv" : true
		},
		{
			"url" : "57414438_p0.png",
			"character" : "Original Character",
			"id" : "57414438",
			"is_pixiv" : true
		},
		{
			"url" : "57330257_p0.png",
			"character" : "ルウシェ, 白猫プロジェクト",
			"id" : "57330257",
			"is_pixiv" : true
		},
		{
			"url" : "57161720_p0.jpg",
			"character" : "Rem, Re Zero",
			"id" : "57161720",
			"is_pixiv" : true
		}

	]
}